hellohuehue/__init__.py
hellohuehue/hello.py
hellohuehue-0.0.2.dist-info/METADATA
hellohuehue-0.0.2.dist-info/WHEEL
hellohuehue-0.0.2.dist-info/top_level.txt
hellohuehue-0.0.2.dist-info/RECORD
