Metadata-Version: 2.1
Name: hellohuehue
Version: 0.0.2
Summary: Hello Pypi huehue package
Author: Anant Mishra
Author-email: amishra_be20@thapar.edu
Keywords: python,video,stream,video stream,camera stream,sockets
Classifier: Development Status :: 1 - Planning
Classifier: Intended Audience :: Developers
Classifier: Programming Language :: Python :: 3
Classifier: Operating System :: Unix
Classifier: Operating System :: MacOS :: MacOS X
Classifier: Operating System :: Microsoft :: Windows
